{"chunk_definitions":[{"row":18,"row_count":1,"visible":true,"expansion_state":0,"options":{"engine":"r","label":"setup","include":false},"document_id":"09D2C7C5","chunk_id":"csetup_chunk","chunk_label":"setup"},{"row":25,"row_count":1,"visible":true,"expansion_state":0,"options":{"engine":"r","label":"unnamed-chunk-2"},"document_id":"09D2C7C5","chunk_id":"c5af63l6ixxew","chunk_label":"unnamed-chunk-1"},{"row":52,"row_count":1,"visible":true,"expansion_state":0,"options":{"engine":"r","label":"unnamed-chunk-67"},"document_id":"09D2C7C5","chunk_id":"c0b3uwl3dds7q","chunk_label":"unnamed-chunk-2"},{"row":77,"row_count":1,"visible":true,"expansion_state":0,"options":{"engine":"r","label":"unnamed-chunk-71"},"document_id":"09D2C7C5","chunk_id":"ceu8relz7tmhj","chunk_label":"unnamed-chunk-3"},{"row":96,"row_count":1,"visible":true,"expansion_state":0,"options":{"engine":"r","label":"unnamed-chunk-75"},"document_id":"09D2C7C5","chunk_id":"cufoo7f311puh","chunk_label":"unnamed-chunk-4"},{"row":118,"row_count":1,"visible":true,"expansion_state":0,"options":{"engine":"r","label":"unnamed-chunk-115"},"document_id":"09D2C7C5","chunk_id":"c3zvzbc1yrc26","chunk_label":"unnamed-chunk-5"},{"row":134,"row_count":1,"visible":true,"expansion_state":0,"options":{"engine":"r","label":"unnamed-chunk-133"},"document_id":"09D2C7C5","chunk_id":"cixch3wnpkaaa","chunk_label":"unnamed-chunk-6"},{"row":152,"row_count":1,"visible":true,"expansion_state":0,"options":{"engine":"r","label":"unnamed-chunk-127"},"document_id":"09D2C7C5","chunk_id":"cokfhtvh28tic","chunk_label":"unnamed-chunk-7"}],"doc_write_time":1644067358,"working_dir":null,"default_chunk_options":{},"chunk_rendered_width":700}